debug/__init__.py
debugger_log-0.1.0.dist-info/licenses/LICENSE
debugger_log-0.1.0.dist-info/METADATA
debugger_log-0.1.0.dist-info/WHEEL
debugger_log-0.1.0.dist-info/top_level.txt
debugger_log-0.1.0.dist-info/RECORD
