Metadata-Version: 2.4
Name: debugger-log
Version: 0.1.0
Summary: A lightweight Python logging utility with colorful console output.
Author-email: Bhargav Barman <bhargavbprd@gmail.com>
License: MIT
Project-URL: Homepage, https://github.com/Bhargavxyz738/debug
Project-URL: Bug Tracker, https://github.com/Bhargavxyz738/debug/issues
Keywords: logging,debug,console,color,terminal
Classifier: Programming Language :: Python :: 3
Classifier: License :: OSI Approved :: MIT License
Classifier: Operating System :: OS Independent
Requires-Python: >=3.7
License-File: LICENSE
Dynamic: license-file
